TOPSIS.py
TOPSIS_Akash_101803431-0.0.4.dist-info/LICENSE.txt
TOPSIS_Akash_101803431-0.0.4.dist-info/METADATA
TOPSIS_Akash_101803431-0.0.4.dist-info/WHEEL
TOPSIS_Akash_101803431-0.0.4.dist-info/entry_points.txt
TOPSIS_Akash_101803431-0.0.4.dist-info/top_level.txt
TOPSIS_Akash_101803431-0.0.4.dist-info/RECORD
